odoo_toolkit/__init__.py
odoo_toolkit/__main__.py
odoo_toolkit/common.py
odoo_toolkit/main.py
odoo_toolkit/dev/__init__.py
odoo_toolkit/dev/common.py
odoo_toolkit/dev/start.py
odoo_toolkit/dev/start_db.py
odoo_toolkit/dev/stop.py
odoo_toolkit/docker/compose.yaml
odoo_toolkit/docker/odoo/.bash_aliases
odoo_toolkit/docker/odoo/append.bashrc
odoo_toolkit/docker/odoo/jammy.Dockerfile
odoo_toolkit/docker/odoo/noble.Dockerfile
odoo_toolkit/docker/odoo/starship.toml
odoo_toolkit/docker/odoo/startup.sh
odoo_toolkit/docker/pgadmin/servers.json
odoo_toolkit/multiverse_config/requirements.txt
odoo_toolkit/multiverse_config/ruff.toml
odoo_toolkit/multiverse_config/.vscode/extensions.json
odoo_toolkit/multiverse_config/.vscode/launch.json
odoo_toolkit/multiverse_config/.vscode/settings.json
odoo_toolkit/mv/__init__.py
odoo_toolkit/mv/common.py
odoo_toolkit/mv/reset.py
odoo_toolkit/mv/setup.py
odoo_toolkit/mv/switch.py
odoo_toolkit/po/__init__.py
odoo_toolkit/po/cldr.csv
odoo_toolkit/po/common.py
odoo_toolkit/po/create.py
odoo_toolkit/po/export.py
odoo_toolkit/po/update.py
odoo_toolkit/po/cldr-common-47/LICENSE
odoo_toolkit/po/cldr-common-47/common/dtd/ldmlSupplemental.dtd
odoo_toolkit/po/cldr-common-47/common/supplemental/plurals.xml
odoo_toolkit/wl/__init__.py
odoo_toolkit/wl/common.py
odoo_toolkit/wl/config.py
odoo_toolkit/wl/copy.py
odoo_toolkit/wl/update_teams.py
odoo_toolkit-1.1.0.dist-info/METADATA
odoo_toolkit-1.1.0.dist-info/WHEEL
odoo_toolkit-1.1.0.dist-info/entry_points.txt
odoo_toolkit-1.1.0.dist-info/licenses/LICENSE
odoo_toolkit-1.1.0.dist-info/RECORD
