Metadata-Version: 2.4
Name: odoo-toolkit
Version: 1.1.0
Summary: This toolkit contains a few useful tools for Odoo development.
Author-email: Dylan Kiss <dyki@odoo.com>
License-File: LICENSE
Requires-Python: ~=3.10
Requires-Dist: gitpython<4,>=3.1.44
Requires-Dist: polib<2,>=1.2.0
Requires-Dist: python-on-whales<0.77,>=0.76.1
Requires-Dist: requests>=2.32.4
Requires-Dist: typer==0.15.4
